{"id":"gnome-tweaks","name":"GNOME Tweaks","summary":"Công cụ tùy chỉnh nâng cao cho môi trường GNOME","description":"GNOME Tweaks cho phép tùy chỉnh nhiều cài đặt của GNOME Desktop vượt ra ngoài Settings thông thường, như font chữ, theme, icon, animation, titlebar và hành vi cửa sổ.","category":"system","icon":"gnome-tweaks","version":"46.0","author":"GNOME Project","license":"GPL-3.0","website":"https://gitlab.gnome.org/GNOME/gnome-tweaks","script":"","tags":["gnome","tùy chỉnh","theme","desktop","tweaks"],"install_methods":[{"pm":"apt","package":"gnome-tweaks"},{"pm":"dnf","package":"gnome-tweaks"},{"pm":"pacman","package":"gnome-tweaks"},{"pm":"flatpak","package":"org.gnome.tweaks"}]}
