{"id":"okular","name":"Okular","summary":"Trình đọc tài liệu đa năng của KDE","description":"Okular là trình đọc tài liệu của KDE hỗ trợ nhiều định dạng như PDF, EPUB, DjVu, CBR/CBZ (comic), ODT và nhiều hơn nữa. Cho phép chú thích, highlight và điền form PDF.","category":"utilities","icon":"okular","version":"24.02","author":"KDE","license":"GPL-2.0","website":"https://okular.kde.org/","script":"","tags":["pdf","ebook","đọc sách","tài liệu","kde"],"install_methods":[{"pm":"apt","package":"okular"},{"pm":"dnf","package":"okular"},{"pm":"pacman","package":"okular"},{"pm":"flatpak","package":"org.kde.okular"},{"pm":"snap","package":"okular"}]}
